CHANGELOG.md
LICENSE
MANIFEST.in
README.md
setup.cfg
setup.py
versioneer.py
src/dev_studio_extensions/__init__.py
src/dev_studio_extensions/flow/__init__.py
src/dev_studio_extensions/flow/flow_extensions/__init__.py
src/dev_studio_extensions/flow/flow_extensions/gui.py
src/dev_studio_extensions/flow/flow_extensions/extensions/__init__.py
src/dev_studio_extensions/flow/flow_extensions/extensions/unittest.py
src/dev_studio_extensions/flow/flow_extensions/project/__init__.py
src/kabaret/__init__.py
src/kabaret.flow_extensions.egg-info/PKG-INFO
src/kabaret.flow_extensions.egg-info/SOURCES.txt
src/kabaret.flow_extensions.egg-info/dependency_links.txt
src/kabaret.flow_extensions.egg-info/requires.txt
src/kabaret.flow_extensions.egg-info/top_level.txt
src/kabaret/flow_extensions/__init__.py
src/kabaret/flow_extensions/_version.py
src/kabaret/flow_extensions/actor/__init__.py
src/kabaret/flow_extensions/flow/__init__.py
src/kabaret/flow_extensions/flow/utils.py
src/kabaret/flow_extensions/ui/__init__.py
src/kabaret/flow_extensions/ui/icons/__init__.py
src/kabaret/flow_extensions/ui/icons/extension.png